spirvsmith_server_sdk/__init__.py
spirvsmith_server_sdk/api/__init__.py
spirvsmith_server_sdk/api/default_api.py
spirvsmith_server_sdk/api/default_api_endpoints/__init__.py
spirvsmith_server_sdk/api/default_api_endpoints/flush_queues_queues_delete.py
spirvsmith_server_sdk/api/default_api_endpoints/get_next_shader_shaders_next_post.py
spirvsmith_server_sdk/api/default_api_endpoints/get_queue_queues_queue_id_get.py
spirvsmith_server_sdk/api/default_api_endpoints/get_queues_queues_get.py
spirvsmith_server_sdk/api/default_api_endpoints/get_shader_shaders_shader_id_get.py
spirvsmith_server_sdk/api/default_api_endpoints/register_executor_queues_put.py
spirvsmith_server_sdk/api/default_api_endpoints/register_generator_generators_post.py
spirvsmith_server_sdk/api/default_api_endpoints/submit_buffers_buffers_shader_id_post.py
spirvsmith_server_sdk/api/default_api_endpoints/submit_shader_shaders_post.py
spirvsmith_server_sdk/api_client.py
spirvsmith_server_sdk/apis/__init__.py
spirvsmith_server_sdk/configuration.py
spirvsmith_server_sdk/docs/BufferSubmission.md
spirvsmith_server_sdk/docs/DefaultApi.md
spirvsmith_server_sdk/docs/ExecutionPlatform.md
spirvsmith_server_sdk/docs/ExecutionQueue.md
spirvsmith_server_sdk/docs/ExecutionQueues.md
spirvsmith_server_sdk/docs/FuzzingStrategy.md
spirvsmith_server_sdk/docs/GeneratorInfo.md
spirvsmith_server_sdk/docs/HTTPValidationError.md
spirvsmith_server_sdk/docs/HardwareInformation.md
spirvsmith_server_sdk/docs/HardwareType.md
spirvsmith_server_sdk/docs/HardwareVendor.md
spirvsmith_server_sdk/docs/MutationsConfig.md
spirvsmith_server_sdk/docs/OperatingSystem.md
spirvsmith_server_sdk/docs/RetrievedShader.md
spirvsmith_server_sdk/docs/ShaderSubmission.md
spirvsmith_server_sdk/docs/ValidationError.md
spirvsmith_server_sdk/docs/VulkanBackend.md
spirvsmith_server_sdk/exceptions.py
spirvsmith_server_sdk/model/__init__.py
spirvsmith_server_sdk/model/buffer_submission.py
spirvsmith_server_sdk/model/execution_platform.py
spirvsmith_server_sdk-0.2.0.dist-info/WHEEL
spirvsmith_server_sdk-0.2.0.dist-info/METADATA
spirvsmith_server_sdk-0.2.0.dist-info/RECORD
