Metadata-Version: 2.1
Name: spirvsmith-server-sdk
Version: 0.2.0
Summary: 
Author: Rayan Hatout
Author-email: rayan.hatout@gmail.com
Requires-Python: >=3.10,<4.0
Classifier: Programming Language :: Python :: 3
Classifier: Programming Language :: Python :: 3.10
Requires-Dist: python-dateutil (>=2.8.2,<3.0.0)
Requires-Dist: urllib3 (>=1.26.9,<2.0.0)
